csc_v2/__init__.py
csc_v2/csc_lite.py
csc_v2/screen_models/Hamming/avana_patched_Hamming_string.pl
csc_v2/screen_models/Hamming/brunello_patch_format_screen_Hamming_string.pl
csc_v2/screen_models/Hamming/geckov1_patch_format_screen_Hamming_string.pl
csc_v2/screen_models/Hamming/geckov2_patch_format_screen_Hamming_string.pl
csc_v2/screen_models/Hamming/project_score_patch_format_screen_Hamming_string.pl
csc_v2/screen_models/Hamming/sabatini_patch_format_screen_Hamming_string.pl
csc_v2/screen_models/examples/avana_patched_sample_gRNA.csv
csc_v2/screen_models/examples/avana_patched_sample_gRNA_lognorm_lnfc.csv
crispr_CSC-0.5.dist-info/LICENSE.txt
crispr_CSC-0.5.dist-info/METADATA
crispr_CSC-0.5.dist-info/WHEEL
crispr_CSC-0.5.dist-info/dependency_links.txt
crispr_CSC-0.5.dist-info/entry_points.txt
crispr_CSC-0.5.dist-info/top_level.txt
crispr_CSC-0.5.dist-info/RECORD
